{
    "build_time": "2026-01-18T15:48:16.931296568",
    "data": {},
    "latest_commit": "87d7d2a",
    "name": "shortcircuit-xt",
    "project_repo": "https://github.com/surge-synthesizer/shortcircuit-xt",
    "recent_commits": [
        {
            "author": "Paul",
            "commit": "87d7d2a",
            "date": "2026-01-18T10:26:28-05:00",
            "message": "Add optional initVoiceEfffectPitch path (#2097)"
        },
        {
            "author": "Paul",
            "commit": "86087f6",
            "date": "2026-01-17T13:09:13-05:00",
            "message": "Move the src/ cmake/ and scripts/ and . license to MIT (#2096)"
        },
        {
            "author": "Paul",
            "commit": "5964a0c",
            "date": "2026-01-16T21:39:32-05:00",
            "message": "Implement build flags for VST3, AUv2, Standalone, etc... (#2095)"
        },
        {
            "author": "Andreya-Autumn",
            "commit": "a43709a",
            "date": "2026-01-17T02:46:52+01:00",
            "message": "Finish tetrad, add resonators category"
        },
        {
            "author": "Andreya-Autumn",
            "commit": "325b5c3",
            "date": "2026-01-16T02:24:50+01:00",
            "message": "Get your tetrads on (#2090)"
        }
    ],
    "releases": {
        "linux64": "https://github.com/surge-synthesizer/shortcircuit-xt/releases/download/Nightly/ShortcircuitXT-2026-01-18-87d7d2a-Linux.zip",
        "macos": "https://github.com/surge-synthesizer/shortcircuit-xt/releases/download/Nightly/shortcircuit-xt-macOS-2026-01-18-87d7d2a.dmg",
        "other": "https://github.com/shortcircuit-xt/releases-xt/releases/tag/Nightly",
        "win64": "https://github.com/surge-synthesizer/shortcircuit-xt/releases/download/Nightly/ShortcircuitXT-2026-01-18-87d7d2a-Windows-64bit.exe",
        "win64zip": "https://github.com/surge-synthesizer/shortcircuit-xt/releases/download/Nightly/ShortcircuitXT-2026-01-18-87d7d2a-Windows-64bit.zip"
    },
    "version": "main"
}