{
    "build_time": "2026-05-29T23:00:46.751646732",
    "data": {},
    "latest_commit": "074ff16",
    "name": "shortcircuit-xt",
    "project_repo": "https://github.com/surge-synthesizer/shortcircuit-xt",
    "recent_commits": [
        {
            "author": "Paul",
            "commit": "074ff16",
            "date": "2026-05-29T18:38:43-04:00",
            "message": "Transpose SelectionManager Topology; Store in SCP (#2489)"
        },
        {
            "author": "Paul",
            "commit": "9f426fc",
            "date": "2026-05-28T12:03:10-04:00",
            "message": "Decouple per-part MIDI channel from global OmniFlavor (#2472)"
        },
        {
            "author": "Paul",
            "commit": "3ee704f",
            "date": "2026-05-27T18:49:32-04:00",
            "message": "Handle SF2 Initial Attenuation (#2486)"
        },
        {
            "author": "Paul",
            "commit": "fea0a74",
            "date": "2026-05-27T08:43:53-04:00",
            "message": "Add foldable groups in the group/zone tree sidebar (#2484)"
        },
        {
            "author": "Paul",
            "commit": "b8793d4",
            "date": "2026-05-26T11:07:56-04:00",
            "message": "Processor and Param Short Names (#2483)"
        }
    ],
    "releases": {
        "linux64": "https://github.com/surge-synthesizer/shortcircuit-xt/releases/download/Nightly/ShortcircuitXT-2026-05-29-074ff16-Linux.zip",
        "macos": "https://github.com/surge-synthesizer/shortcircuit-xt/releases/download/Nightly/shortcircuit-xt-macOS-2026-05-29-074ff16.dmg",
        "other": "https://github.com/surge-synthesizer/shortcircuit-xt/releases/tag/Nightly",
        "win64": "https://github.com/surge-synthesizer/shortcircuit-xt/releases/download/Nightly/ShortcircuitXT-2026-05-29-074ff16-Windows-64bit.exe",
        "win64zip": "https://github.com/surge-synthesizer/shortcircuit-xt/releases/download/Nightly/ShortcircuitXT-2026-05-29-074ff16-Windows-64bit.zip"
    },
    "version": "main"
}