{
    "build_time": "2026-01-31T14:53:57.985237666",
    "data": {},
    "latest_commit": "a09507d",
    "name": "shortcircuit-xt",
    "project_repo": "https://github.com/surge-synthesizer/shortcircuit-xt",
    "recent_commits": [
        {
            "author": "Paul",
            "commit": "a09507d",
            "date": "2026-01-31T09:15:26-05:00",
            "message": "Add processor copy and paste; Introduce pure ui-side cnp (#2147)"
        },
        {
            "author": "Paul",
            "commit": "bfc7fc3",
            "date": "2026-01-30T17:59:23-05:00",
            "message": "This may be my awesome multi (#2144)"
        },
        {
            "author": "Paul",
            "commit": "b6b70ec",
            "date": "2026-01-30T14:45:24-05:00",
            "message": "Beta language"
        },
        {
            "author": "Paul",
            "commit": "fccb096",
            "date": "2026-01-30T13:59:49-05:00",
            "message": "File Comment only update (#2142)"
        },
        {
            "author": "Paul",
            "commit": "b8f76f1",
            "date": "2026-01-30T13:27:43-05:00",
            "message": "Keyswitch group trigger first draft (#2141)"
        }
    ],
    "releases": {
        "linux64": "https://github.com/surge-synthesizer/shortcircuit-xt/releases/download/Nightly/ShortcircuitXT-2026-01-31-a09507d-Linux.zip",
        "macos": "https://github.com/surge-synthesizer/shortcircuit-xt/releases/download/Nightly/shortcircuit-xt-macOS-2026-01-31-a09507d.dmg",
        "other": "https://github.com/shortcircuit-xt/releases-xt/releases/tag/Nightly",
        "win64": "https://github.com/surge-synthesizer/shortcircuit-xt/releases/download/Nightly/ShortcircuitXT-2026-01-31-a09507d-Windows-64bit.exe",
        "win64zip": "https://github.com/surge-synthesizer/shortcircuit-xt/releases/download/Nightly/ShortcircuitXT-2026-01-31-a09507d-Windows-64bit.zip"
    },
    "version": "main"
}